concierge_keycloak/__init__.py
concierge_keycloak-0.1a1.dist-info/METADATA
concierge_keycloak-0.1a1.dist-info/WHEEL
concierge_keycloak-0.1a1.dist-info/RECORD
