Metadata-Version: 2.4
Name: concierge-keycloak
Version: 0.1a1
Requires-Python: >=3.12
Requires-Dist: python-keycloak
